auto_extract/__init__.py
auto_extract/__main__.py
auto_extract/content.py
auto_extract/extract_item.py
auto_extract/images.py
auto_extract/jsonld.py
auto_extract/language.py
auto_extract/title.py
auto_extract/utils.py
auto_extract/view.py
auto_extract/crawling/__init__.py
auto_extract/crawling/block.py
auto_extract/crawling/crawler.py
auto_extract/crawling/medium.py
auto_extract/crawling/regexes.py
auto_extract/crawling/steemit.py
auto_extract/crawling/storage.py
auto_extract-0.1.3.dist-info/METADATA
auto_extract-0.1.3.dist-info/WHEEL
auto_extract-0.1.3.dist-info/entry_points.txt
auto_extract-0.1.3.dist-info/top_level.txt
auto_extract-0.1.3.dist-info/RECORD
